[
{
  "model": "materials.lesson",
  "pk": 2,
  "fields": {
    "title": "Биология",
    "description": "Краткий экскурс в мир животных",
    "image": "",
    "link": null,
    "course": 1,
    "owner": null
  }
},
{
  "model": "materials.lesson",
  "pk": 3,
  "fields": {
    "title": "География",
    "description": "5-9 класс.",
    "image": "",
    "link": null,
    "course": 1,
    "owner": null
  }
},
{
  "model": "materials.lesson",
  "pk": 5,
  "fields": {
    "title": "Информатика",
    "description": "Основы программирования",
    "image": "",
    "link": null,
    "course": 1,
    "owner": null
  }
},
{
  "model": "materials.lesson",
  "pk": 8,
  "fields": {
    "title": "ОБЖ",
    "description": "Основы жизнедеятельности",
    "image": "",
    "link": null,
    "course": 2,
    "owner": null
  }
},
{
  "model": "materials.lesson",
  "pk": 9,
  "fields": {
    "title": "Химия",
    "description": "Секреты H2O",
    "image": "",
    "link": null,
    "course": 1,
    "owner": 9
  }
},
{
  "model": "materials.lesson",
  "pk": 10,
  "fields": {
    "title": "Химия 2/0",
    "description": "Секреты H2O",
    "image": "",
    "link": null,
    "course": 1,
    "owner": 9
  }
}
]
